facefinder-0.1.11.dist-info/METADATA
facefinder-0.1.11.dist-info/WHEEL
facefinder/interact.py
facefinder/metadata.py
facefinder/metrics.py
facefinder/prompting.py
facefinder/search.py
facefinder/__init__.py
facefinder/rust.cp310-win_amd64.pyd
facefinder-0.1.11.dist-info/RECORD
